bannotator/__init__.py
bannotator/app.py
bannotator/data.py
bannotator/dataview.py
bannotator/dialog.py
bannotator/mainwindow.py
bannotator/state.py
bannotator/utility.py
bannotator/video.py
bannotator/widgets.py
bannotator/resources/app_illustration.png
bannotator/resources/app_screenshot.png
bannotator/resources/behavior annotator-1.png
bannotator/resources/behavior annotattor-transparent.png
bannotator/resources/bg.png
bannotator/resources/bg_readme.png
bannotator/resources/icon.icns
bannotator/resources/icon.ico
bannotator/resources/icon.png
bannotator/resources/new_annotation_dialog.png
bannotator/resources/resource.qrc
bannotator/resources/resource_rc.py
bannotator/ui/__init__.py
bannotator/ui/dump_ui.py
bannotator/ui/ui_add_behavior_dialog.py
bannotator/ui/ui_add_stream_dialog.py
bannotator/ui/ui_delete_behavior_dialog.py
bannotator/ui/ui_delete_stream_dialog.py
bannotator/ui/ui_mainwindow.py
bannotator/ui/ui_new_annotation_dialog.py
bannotator/ui/ui_truncate_annotation_dialog.py
bannotator-1.0.0.dist-info/LICENSE
bannotator-1.0.0.dist-info/METADATA
bannotator-1.0.0.dist-info/WHEEL
bannotator-1.0.0.dist-info/entry_points.txt
bannotator-1.0.0.dist-info/top_level.txt
bannotator-1.0.0.dist-info/RECORD
