Metadata-Version: 2.1
Name: bannotator
Version: 1.0.0
Summary: Anntotate episodic events of videos
Author-email: Xingjian Zhang <hsingchien.zhang@gmail.com>
License: MIT License
Project-URL: Homepage, https://github.com/hsingchien/Bannotator
Keywords: video,annotate,gui
Classifier: License :: OSI Approved :: MIT License
Classifier: Programming Language :: Python
Classifier: Programming Language :: Python :: 3
Classifier: Development Status :: 4 - Beta
Classifier: Topic :: Software Development :: User Interfaces
Requires-Python: >=3.9
License-File: LICENSE
Requires-Dist: numpy >=1.23.0
Requires-Dist: scipy >=1.10
Requires-Dist: opencv-python >=4.7.0
Requires-Dist: pyside6 >=6.4.2
Requires-Dist: distinctipy >=1.2.2
Provides-Extra: dev
Requires-Dist: black ; extra == 'dev'
Requires-Dist: bumpver ; extra == 'dev'
Requires-Dist: pytest ; extra == 'dev'
Requires-Dist: scikit-learn ; extra == 'dev'
